{
  "config":{
    "query_token_id":"[unused0]",
    "doc_token_id":"[unused1]",
    "query_token":"[Q]",
    "doc_token":"[D]",
    "ncells":null,
    "centroid_score_threshold":null,
    "ndocs":null,
    "load_index_with_mmap":false,
    "index_path":null,
    "index_bsize":32,
    "nbits":8,
    "kmeans_niters":20,
    "resume":false,
    "similarity":"cosine",
    "bsize":64,
    "accumsteps":1,
    "lr":0.00001,
    "maxsteps":400000,
    "save_every":null,
    "warmup":20000,
    "warmup_bert":null,
    "relu":false,
    "nway":64,
    "use_ib_negatives":true,
    "reranker":false,
    "distillation_alpha":1.0,
    "ignore_scores":false,
    "model_name":null,
    "query_maxlen":32,
    "attend_to_mask_tokens":false,
    "interaction":"colbert",
    "dim":128,
    "doc_maxlen":256,
    "mask_punctuation":true,
    "checkpoint":"colbert-ir/colbertv2.0",
    "triples":"/future/u/okhattab/root/unit/experiments/2021.10/downstream.distillation.round2.2_score/round2.nway6.cosine.ib/examples.64.json",
    "collection":[
      "list with 1000 elements starting with...",
      [
        "query_need_to_answer:\nthe scheduled date for the farm with 17 turbine be 2012\ntable_formatted:\n|    | wind farm          | scheduled                   |   capacity (mw) |   turbines | type               | location         |\n|---:|:-------------------|:----------------------------|----------------:|-----------:|:-------------------|:-----------------|\n|  0 | codling            | unknown                     |          1100   |        220 | unknown            | county wicklow   |\n|  1 | carrowleagh        | 2012                        |            36.8 |         16 | enercon e - 70 2.3 | county cork      |\n|  2 | dublin array       | 2015                        |           364   |        145 | unknown            | county dublin    |\n|  3 | glenmore           | 2009 summer                 |            30   |         10 | vestas v90         | county clare     |\n|  4 | glenough           | 2010 winter                 |            32.5 |         13 | nordex n80 / n90   | county tipperary |\n|  5 | gortahile          | 2010 autumn                 |            20   |          8 | nordex n90         | county laois     |\n|  6 | grouse lodge       | 2011 summer                 |            20   |          8 | nordex n90         | county tipperary |\n|  7 | moneypoint         | unknown                     |            22.5 |          9 | unknown            | county clare     |\n|  8 | mount callan       | unknown                     |            90   |         30 | 3 mw               | county clare     |\n|  9 | oriel              | 2013                        |           330   |         55 | unknown            | county louth     |\n| 10 | skerd rocks        | unknown                     |           100   |         20 | 5 mw               | county galway    |\n| 11 | shragh             | planning submitted oct 2011 |           135   |         45 | enercon e82 3.0 mw | county clare     |\n| 12 | garracummer        | 2012                        |            42.5 |         17 | nordex n90 2.5 mw  | county tipperary |\n| 13 | knockacummer       | 2013                        |            87.5 |         35 | nordex n90 2.5 mw  | county cork      |\n| 14 | monaincha          | 2013                        |            36   |         15 | nordex n117 2.4 mw | county tipperary |\n| 15 | gibbet hill        | 2013                        |            15   |          6 | nordex n90 2.5 mw  | county wexford   |\n| 16 | glenough extension | 2013                        |             2.5 |          1 | nordex n90 2.5 mw  | county tipperary |\nterms_explanation:\n\ntable_summary:\n\ntable_context:\n",
        "query_need_to_answer:\nall 12 club play a total of 22 game for the wru division one east\ntable_formatted:\n|    | club                 |   played |   drawn |   lost |   points for |   points against |   tries for |   tries against |   try bonus |   losing bonus |   points |\n|---:|:---------------------|---------:|--------:|-------:|-------------:|-----------------:|------------:|----------------:|------------:|---------------:|---------:|\n|  0 | pontypool rfc        |       22 |       2 |      2 |          648 |              274 |          81 |              32 |          12 |              1 |       89 |\n|  1 | caerphilly rfc       |       22 |       2 |      4 |          482 |              316 |          56 |              37 |           7 |              3 |       78 |\n|  2 | blackwood rfc        |       22 |       2 |      6 |          512 |              378 |          60 |              42 |           8 |              3 |       71 |\n|  3 | bargoed rfc          |       22 |       0 |      8 |          538 |              449 |          72 |              52 |          10 |              4 |       70 |\n|  4 | uwic rfc             |       22 |       2 |      7 |          554 |              408 |          71 |              50 |           6 |              2 |       64 |\n|  5 | llanharan rfc        |       22 |       1 |     12 |          436 |              442 |          44 |              51 |           1 |              7 |       46 |\n|  6 | newbridge rfc        |       22 |       2 |     11 |          355 |              400 |          36 |              47 |           2 |              3 |       45 |\n|  7 | rumney rfc           |       22 |       2 |     12 |          435 |              446 |          56 |              52 |           5 |              3 |       44 |\n|  8 | newport saracens rfc |       22 |       0 |     14 |          344 |              499 |          45 |              64 |           2 |              3 |       37 |\n|  9 | beddau rfc           |       22 |       0 |     15 |          310 |              483 |          32 |              61 |           2 |              4 |       34 |\n| 10 | fleur de lys rfc     |       22 |       1 |     16 |          300 |              617 |          34 |              77 |           2 |              4 |       28 |\n| 11 | llantrisant rfc      |       22 |       0 |     18 |          402 |              592 |          55 |              77 |           4 |              6 |       26 |\nterms_explanation:\n\ntable_summary:\n\ntable_context:\n",
        "query_need_to_answer:\ntouchdown atlantic , in the category of sporting , be establish in 2010\ntable_formatted:\n|    | event name                                 |   established | category       | sub category   | main venue               |\n|---:|:-------------------------------------------|--------------:|:---------------|:---------------|:-------------------------|\n|  0 | dieppe kite international                  |          2001 | sporting       | kite flying    | dover park               |\n|  1 | the frye festival                          |          2000 | arts           | literary       | university of moncton    |\n|  2 | hubcap comedy festival                     |          2000 | arts           | comedy         | various                  |\n|  3 | touchdown atlantic                         |          2010 | sporting       | football       | moncton stadium          |\n|  4 | atlantic nationals automotive extravaganza |          2000 | transportation | automotive     | moncton coliseum         |\n|  5 | world wine & food expo                     |          1990 | arts           | food & drink   | moncton coliseum         |\n|  6 | shediac lobster festival                   |          1950 | arts           | food & drink   | shediac festival grounds |\n|  7 | mosa\u00e3\u00afq multicultural festival             |          2004 | festival       | multicultural  | moncton city hall plaza  |\nterms_explanation:\n\ntable_summary:\n\ntable_context:\n"
      ]
    ],
    "queries":"/future/u/okhattab/data/MSMARCO/queries.train.tsv",
    "index_name":"my_index",
    "overwrite":false,
    "root":".ragatouille/",
    "experiment":"colbert",
    "index_root":null,
    "name":"2024-08/11/23.38.14",
    "rank":0,
    "nranks":1,
    "amp":true,
    "gpus":1,
    "avoid_fork_if_possible":false
  },
  "num_chunks":1,
  "num_partitions":4096,
  "num_embeddings":82854,
  "avg_doclen":82.854,
  "RAGatouille":{
    "index_config":{
      "index_type":"PLAID",
      "index_name":"my_index"
    }
  }
}